__init__.py
metaKEGG/__init__.py
metaKEGG/cli.py
metaKEGG/config.py
metaKEGG/helpers/__init__.py
metaKEGG/helpers/helpfunctions.py
metaKEGG/modules/__init__.py
metaKEGG/modules/colorscale.py
metaKEGG/modules/drawing_functions.py
metaKEGG/modules/pipeline.py
metaKEGG/modules/pipeline_async.py
metaKEGG-1.0.1.dist-info/LICENSE
metaKEGG-1.0.1.dist-info/METADATA
metaKEGG-1.0.1.dist-info/WHEEL
metaKEGG-1.0.1.dist-info/top_level.txt
metaKEGG-1.0.1.dist-info/RECORD
