Metadata-Version: 2.1
Name: metaKEGG
Version: 1.0.1
Summary: A python package to map enrichment analysis on KEGG pathways.
Author-email: Michail Lazaratos <Michail.Lazaratos@dife.de>
Maintainer-email: Michail Lazaratos <Michail.Lazaratos@dife.de>
License: AGPL-3.0
Project-URL: Repository, https://github.com/dife-bioinformatics/metaKEGG
Classifier: Intended Audience :: Developers
Classifier: Intended Audience :: Education
Classifier: Intended Audience :: Science/Research
Classifier: Programming Language :: Python :: 3
Classifier: Programming Language :: Python :: 3.9
Classifier: Programming Language :: Python :: 3.10
Classifier: Programming Language :: Python :: 3.11
Classifier: Programming Language :: Python :: 3.12
Classifier: License :: OSI Approved :: GNU Affero General Public License v3 or later (AGPLv3+)
Classifier: Operating System :: OS Independent
Requires-Python: <3.13,>=3.9
License-File: LICENSE
Requires-Dist: matplotlib<3.11,==3.9.2; python_version != "3.9"
Requires-Dist: matplotlib==3.6.2; python_version == "3.9"
Requires-Dist: numpy==1.26.0; python_version == "3.9"
Requires-Dist: numpy==2.1.3; python_version != "3.9"
Requires-Dist: openpyxl==3.1.5
Requires-Dist: pyopenssl==24.2.1
Requires-Dist: pandas==2.2.3
Requires-Dist: pip
Requires-Dist: setuptools==75.6.0
Requires-Dist: setuptools-scm==8.1.0
Requires-Dist: biopython==1.84
Requires-Dist: pypdf2==3.0.1
Requires-Dist: pytest==8.3.3
Requires-Dist: pytest-asyncio==0.24.0
Requires-Dist: reportlab==4.2.5
Requires-Dist: requests==2.32.3
Requires-Dist: xlsxwriter==3.2.0
Requires-Dist: fsspec==2024.10.0
